astroid/__init__.py
astroid/__pkginfo__.py
astroid/_ast.py
astroid/_backport_stdlib_names.py
astroid/arguments.py
astroid/astroid_manager.py
astroid/bases.py
astroid/builder.py
astroid/const.py
astroid/constraint.py
astroid/context.py
astroid/decorators.py
astroid/exceptions.py
astroid/filter_statements.py
astroid/helpers.py
astroid/inference_tip.py
astroid/manager.py
astroid/modutils.py
astroid/objects.py
astroid/protocols.py
astroid/raw_building.py
astroid/rebuilder.py
astroid/test_utils.py
astroid/transforms.py
astroid/typing.py
astroid/util.py
astroid/brain/__init__.py
astroid/brain/brain_argparse.py
astroid/brain/brain_attrs.py
astroid/brain/brain_boto3.py
astroid/brain/brain_builtin_inference.py
astroid/brain/brain_collections.py
astroid/brain/brain_crypt.py
astroid/brain/brain_ctypes.py
astroid/brain/brain_curses.py
astroid/brain/brain_dataclasses.py
astroid/brain/brain_datetime.py
astroid/brain/brain_dateutil.py
astroid/brain/brain_functools.py
astroid/brain/brain_gi.py
astroid/brain/brain_hashlib.py
astroid/brain/brain_http.py
astroid/brain/brain_hypothesis.py
astroid/brain/brain_io.py
astroid/brain/brain_mechanize.py
astroid/brain/brain_multiprocessing.py
astroid/brain/brain_namedtuple_enum.py
astroid/brain/brain_nose.py
astroid/brain/brain_numpy_core_einsumfunc.py
astroid/brain/brain_numpy_core_fromnumeric.py
astroid/brain/brain_numpy_core_function_base.py
astroid/brain/brain_numpy_core_multiarray.py
astroid/brain/brain_numpy_core_numeric.py
astroid/brain/brain_numpy_core_numerictypes.py
astroid/brain/brain_numpy_core_umath.py
astroid/brain/brain_numpy_ma.py
astroid/brain/brain_numpy_ndarray.py
astroid/brain/brain_numpy_random_mtrand.py
astroid/brain/brain_numpy_utils.py
astroid/brain/brain_pathlib.py
astroid/brain/brain_pkg_resources.py
astroid/brain/brain_pytest.py
astroid/brain/brain_qt.py
astroid/brain/brain_random.py
astroid/brain/brain_re.py
astroid/brain/brain_regex.py
astroid/brain/brain_responses.py
astroid/brain/brain_scipy_signal.py
astroid-3.3.1.dist-info/CONTRIBUTORS.txt
astroid-3.3.1.dist-info/LICENSE
astroid-3.3.1.dist-info/METADATA
astroid-3.3.1.dist-info/WHEEL
astroid-3.3.1.dist-info/top_level.txt
astroid-3.3.1.dist-info/RECORD
