Metadata-Version: 2.1
Name: astroid
Version: 3.3.1
Summary: An abstract syntax tree for Python with inference support.
License: LGPL-2.1-or-later
Project-URL: Docs, https://pylint.readthedocs.io/projects/astroid/en/latest/
Project-URL: Source Code, https://github.com/pylint-dev/astroid
Project-URL: Bug tracker, https://github.com/pylint-dev/astroid/issues
Project-URL: Discord server, https://discord.gg/Egy6P8AMB5
Keywords: static code analysis,python,abstract syntax tree
Classifier: Development Status :: 6 - Mature
Classifier: Environment :: Console
Classifier: Intended Audience :: Developers
Classifier: License :: OSI Approved :: GNU Lesser General Public License v2 (LGPLv2)
Classifier: Operating System :: OS Independent
Classifier: Programming Language :: Python
Classifier: Programming Language :: Python :: 3
Classifier: Programming Language :: Python :: 3 :: Only
Classifier: Programming Language :: Python :: 3.9
Classifier: Programming Language :: Python :: 3.10
Classifier: Programming Language :: Python :: 3.11
Classifier: Programming Language :: Python :: 3.12
Classifier: Programming Language :: Python :: 3.13
Classifier: Programming Language :: Python :: Implementation :: CPython
Classifier: Programming Language :: Python :: Implementation :: PyPy
Classifier: Topic :: Software Development :: Libraries :: Python Modules
Classifier: Topic :: Software Development :: Quality Assurance
Classifier: Topic :: Software Development :: Testing
Requires-Python: >=3.9.0
License-File: LICENSE
License-File: CONTRIBUTORS.txt
Requires-Dist: typing-extensions>=4.0.0; python_version < "3.11"
